MANIFEST.in
README.rst
setup.py
indexedproperty/__init__.py
indexedproperty.egg-info/PKG-INFO
indexedproperty.egg-info/SOURCES.txt
indexedproperty.egg-info/dependency_links.txt
indexedproperty.egg-info/top_level.txt
indexedproperty/test/__init__.py
indexedproperty/test/test_cp.py
indexedproperty/test/test_ip.py
indexedproperty/test/test_rp.py