Metadata-Version: 1.1
Name: indexedproperty
Version: 0.1.4
Summary: Properties with item-style access
Home-page: https://github.com/NJDFan/indexedproperty
Author: Rob Gaddi
Author-email: rgaddi@highlandtechnology.com
License: MIT
Keywords: properties
Platform: UNKNOWN
Classifier: Development Status :: 4 - Beta
Classifier: Intended Audience :: Developers
Classifier: License :: OSI Approved :: MIT License
Classifier: Programming Language :: Python :: 3
Classifier: Programming Language :: Python :: 3.4
